odoo/addons/purchase_stock_packaging/README.rst
odoo/addons/purchase_stock_packaging/__init__.py
odoo/addons/purchase_stock_packaging/__manifest__.py
odoo/addons/purchase_stock_packaging/i18n/hr.po
odoo/addons/purchase_stock_packaging/i18n/it.po
odoo/addons/purchase_stock_packaging/i18n/pt_BR.po
odoo/addons/purchase_stock_packaging/i18n/purchase_stock_packaging.pot
odoo/addons/purchase_stock_packaging/i18n/sl.po
odoo/addons/purchase_stock_packaging/models/__init__.py
odoo/addons/purchase_stock_packaging/models/purchase_order_line.py
odoo/addons/purchase_stock_packaging/readme/CONTRIBUTORS.md
odoo/addons/purchase_stock_packaging/readme/DESCRIPTION.md
odoo/addons/purchase_stock_packaging/readme/USAGE.md
odoo/addons/purchase_stock_packaging/static/description/icon.png
odoo/addons/purchase_stock_packaging/static/description/index.html
odoo/addons/purchase_stock_packaging/tests/__init__.py
odoo/addons/purchase_stock_packaging/tests/test_purchase_packaging.py
odoo_addon_purchase_stock_packaging-18.0.1.0.0.5.dist-info/METADATA
odoo_addon_purchase_stock_packaging-18.0.1.0.0.5.dist-info/WHEEL
odoo_addon_purchase_stock_packaging-18.0.1.0.0.5.dist-info/top_level.txt
odoo_addon_purchase_stock_packaging-18.0.1.0.0.5.dist-info/RECORD
