Metadata-Version: 2.1
Name: odoo-addon-purchase_stock_packaging
Version: 18.0.1.0.0.5
Requires-Python: >=3.10
Requires-Dist: odoo==18.0.*
Summary: Allows to transmit the product packaging from the procurement values to the generated purchase order line
Home-page: https://github.com/OCA/purchase-workflow
License: AGPL-3
Author: ACSONE SA/NV,ForgeFlow,Odoo Community Association (OCA)
Author-email: support@odoo-community.org
Classifier: Programming Language :: Python
Classifier: Framework :: Odoo
Classifier: Framework :: Odoo :: 18.0
Classifier: License :: OSI Approved :: GNU Affero General Public License v3
